test.py
image_tpu/__init__.py
image_tpu/tpu.py
image_tpu-0.1.1.dist-info/LICENCE
image_tpu-0.1.1.dist-info/METADATA
image_tpu-0.1.1.dist-info/WHEEL
image_tpu-0.1.1.dist-info/top_level.txt
image_tpu-0.1.1.dist-info/RECORD
