Metadata-Version: 2.1
Name: image_tpu
Version: 0.1.1
Summary: A Python package to control images!
Author: itsmajid
Classifier: Programming Language :: Python :: 3
Classifier: License :: OSI Approved :: MIT License
Classifier: Operating System :: OS Independent
Requires-Python: >=3.8
License-File: LICENCE
